nameko_atomicity/__init__.py
nameko_atomicity/commands.py
nameko_atomicity/dispatch_commands.py
nameko_atomicity/exceptions.py
nameko_atomicity/rollback_commands.py
nameko_atomicity-1.0.0.dist-info/LICENSE
nameko_atomicity-1.0.0.dist-info/METADATA
nameko_atomicity-1.0.0.dist-info/WHEEL
nameko_atomicity-1.0.0.dist-info/top_level.txt
nameko_atomicity-1.0.0.dist-info/zip-safe
nameko_atomicity-1.0.0.dist-info/RECORD
